bonicbot_bridge/__init__.py
bonicbot_bridge/camera.py
bonicbot_bridge/core.py
bonicbot_bridge/exceptions.py
bonicbot_bridge/motion.py
bonicbot_bridge/sensors.py
bonicbot_bridge/servo.py
bonicbot_bridge/system.py
bonicbot_bridge-0.2.3.dist-info/licenses/LICENSE
bonicbot_bridge-0.2.3.dist-info/METADATA
bonicbot_bridge-0.2.3.dist-info/WHEEL
bonicbot_bridge-0.2.3.dist-info/entry_points.txt
bonicbot_bridge-0.2.3.dist-info/top_level.txt
bonicbot_bridge-0.2.3.dist-info/RECORD
